{"legislative_session": "2025-2026", "identifier": "HSB 282", "title": "A bill for an act relating to cooperation by public and private schools with federal immigration and customs enforcement officers.", "from_organization": "~{\"classification\": \"lower\"}", "classification": ["proposed bill"], "subject": ["immigration", "private education", "school districts"], "abstracts": [], "other_titles": [], "other_identifiers": [], "actions": [{"description": "Introduced, referred to Education.", "date": "2025-03-04", "organization_id": "~{\"classification\": \"lower\"}", "classification": ["introduction", "referral-committee"], "related_entities": []}, {"description": "Subcommittee: Wheeler, Stone and Wessel-Kroeschell.", "date": "2025-03-04", "organization_id": "~{\"classification\": \"lower\"}", "classification": [], "related_entities": []}], "sponsorships": [{"name": "COMMITTEE ON EDUCATION", "classification": "primary", "entity_type": "organization", "primary": true, "person_id": null, "organization_id": "~{\"name\": \"COMMITTEE ON EDUCATION\"}"}], "related_bills": [], "versions": [{"note": "Introduced", "links": [{"url": "https://www.legis.iowa.gov/docs/publications/LGI/91/attachments/HSB282.html", "media_type": "text/html"}, {"url": "https://www.legis.iowa.gov/docs/publications/LGI/91/HSB282.pdf", "media_type": "application/pdf"}], "date": "", "classification": ""}], "documents": [], "citations": [], "sources": [{"url": "https://www.legis.iowa.gov/legislation/billTracking/billHistory?billName=HSB 282&ga=91", "note": ""}], "extras": {}, "jurisdiction": {"id": "ocd-jurisdiction/country:us/state:ia/government", "name": "Iowa", "classification": "state", "division_id": "ocd-division/country:us/state:ia"}, "scraped_at": "2026-01-04T08:15:35+00:00", "_id": "8bc97366-e945-11f0-998b-66e600971d5b"}