{"legislative_session": "2025-2026", "identifier": "HF 2256", "title": "A bill for an act relating to adjudication of a child in need of assistance due to the need for treatment of a chemical dependency, mental health disorder, or behavioral disorder.", "from_organization": "~{\"classification\": \"lower\"}", "classification": ["bill"], "subject": ["child assistance", "juvenile justice", "mental health", "substance use disorder"], "abstracts": [], "other_titles": [], "other_identifiers": [], "actions": [{"description": "Introduced, placed on calendar.", "date": "2026-01-30", "organization_id": "~{\"classification\": \"lower\"}", "classification": ["introduction"], "related_entities": []}], "sponsorships": [{"name": "COMMITTEE ON HEALTH AND HUMAN SERVICES", "classification": "primary", "entity_type": "organization", "primary": true, "person_id": null, "organization_id": "~{\"name\": \"COMMITTEE ON HEALTH AND HUMAN SERVICES\"}"}], "related_bills": [], "versions": [{"note": "Introduced", "links": [{"url": "https://www.legis.iowa.gov/docs/publications/LGI/91/attachments/HF2256.html", "media_type": "text/html"}, {"url": "https://www.legis.iowa.gov/docs/publications/LGI/91/HF2256.pdf", "media_type": "application/pdf"}], "date": "", "classification": ""}], "documents": [], "citations": [], "sources": [{"url": "https://www.legis.iowa.gov/legislation/billTracking/billHistory?billName=HF 2256&ga=91", "note": ""}], "extras": {}, "jurisdiction": {"id": "ocd-jurisdiction/country:us/state:ia/government", "name": "Iowa", "classification": "state", "division_id": "ocd-division/country:us/state:ia"}, "scraped_at": "2026-02-14T08:18:55+00:00", "_id": "ce2b709e-097d-11f1-8017-220d11a58005"}