{"legislative_session": "2025-2026", "identifier": "SF 2314", "title": "A bill for an act relating to executive branch functions, including ratification of major administrative rules and certain other actions, other matters relating to the state rulemaking process, and terms of service of certain appointed members of certain boards, and including applicability provisions.", "from_organization": "~{\"classification\": \"upper\"}", "classification": ["bill"], "subject": ["administrative procedure", "administrative rules", "administrative rules coordinator", "district courts", "executive branch", "legislative branch", "legislative council", "legislative services agency", "notices"], "abstracts": [], "other_titles": [], "other_identifiers": [], "actions": [{"description": "Introduced, referred to State Government.", "date": "2026-02-12", "organization_id": "~{\"classification\": \"upper\"}", "classification": ["introduction", "referral-committee"], "related_entities": []}, {"description": "Subcommittee: Webster, Bousselot, and Winckler.", "date": "2026-02-12", "organization_id": "~{\"classification\": \"upper\"}", "classification": [], "related_entities": []}], "sponsorships": [{"name": "WEBSTER", "classification": "primary", "entity_type": "person", "primary": true, "person_id": "~{\"name\": \"WEBSTER\"}", "organization_id": null}], "related_bills": [], "versions": [{"note": "Introduced", "links": [{"url": "https://www.legis.iowa.gov/docs/publications/LGI/91/attachments/SF2314.html", "media_type": "text/html"}, {"url": "https://www.legis.iowa.gov/docs/publications/LGI/91/SF2314.pdf", "media_type": "application/pdf"}], "date": "", "classification": ""}], "documents": [], "citations": [], "sources": [{"url": "https://www.legis.iowa.gov/legislation/billTracking/billHistory?billName=SF 2314&ga=91", "note": ""}], "extras": {}, "jurisdiction": {"id": "ocd-jurisdiction/country:us/state:ia/government", "name": "Iowa", "classification": "state", "division_id": "ocd-division/country:us/state:ia"}, "scraped_at": "2026-02-13T08:31:19+00:00", "_id": "5f2edcde-08b6-11f1-ad57-aed5550d705c"}