{"legislative_session": "2025-2026", "identifier": "SSB 1185", "title": "A bill for an act concerning county and city regulation of real property and the powers granted to a board of adjustment.", "from_organization": "~{\"classification\": \"upper\"}", "classification": ["proposed bill"], "subject": ["boards, commissions, and councils", "city councils", "city government", "county boards of supervisors", "county government", "ordinances", "property", "real property", "zoning"], "abstracts": [], "other_titles": [], "other_identifiers": [], "actions": [{"description": "Introduced, referred to Commerce.", "date": "2025-02-25", "organization_id": "~{\"classification\": \"legislature\"}", "classification": ["introduction", "referral-committee"], "related_entities": []}, {"description": "Subcommittee: Webster, Klimesh, and Wahls.", "date": "2025-02-25", "organization_id": "~{\"classification\": \"legislature\"}", "classification": [], "related_entities": []}, {"description": "Subcommittee Meeting: 03/04/2025 1:00PM Senate Lounge.", "date": "2025-03-03", "organization_id": "~{\"classification\": \"legislature\"}", "classification": [], "related_entities": []}, {"description": "Subcommittee recommends passage.", "date": "2025-03-04", "organization_id": "~{\"classification\": \"legislature\"}", "classification": ["committee-passage-favorable"], "related_entities": []}, {"description": "Committee report approving bill, renumbered as SF 569.", "date": "2025-03-06", "organization_id": "~{\"classification\": \"legislature\"}", "classification": ["committee-passage"], "related_entities": []}], "sponsorships": [{"name": "COMMITTEE ON COMMERCE", "classification": "primary", "entity_type": "organization", "primary": true, "person_id": null, "organization_id": "~{\"name\": \"COMMITTEE ON COMMERCE\"}"}], "related_bills": [], "versions": [{"note": "Introduced", "links": [{"url": "https://www.legis.iowa.gov/docs/publications/LGI/91/attachments/SSB1185.html", "media_type": "text/html"}, {"url": "https://www.legis.iowa.gov/docs/publications/LGI/91/SSB1185.pdf", "media_type": "application/pdf"}], "date": "", "classification": ""}], "documents": [], "citations": [], "sources": [{"url": "https://www.legis.iowa.gov/legislation/billTracking/billHistory?billName=SSB 1185&ga=91", "note": ""}], "extras": {}, "jurisdiction": {"id": "ocd-jurisdiction/country:us/state:ia/government", "name": "Iowa", "classification": "state", "division_id": "ocd-division/country:us/state:ia"}, "scraped_at": "2026-01-10T08:14:31+00:00", "_id": "6406ffd6-edfc-11f0-a607-4e346869e335"}