{"legislative_session": "2025-2026", "identifier": "HF 896", "title": "A bill for an act relating to the maximum driving distance for persons issued a special minor\u2019s restricted driver\u2019s license who participate in open enrollment.", "from_organization": "~{\"classification\": \"lower\"}", "classification": ["bill"], "subject": ["driver's licenses", "driving", "open enrollment", "students"], "abstracts": [], "other_titles": [], "other_identifiers": [], "actions": [{"description": "Introduced, placed on calendar.", "date": "2025-03-07", "organization_id": "~{\"classification\": \"lower\"}", "classification": ["introduction"], "related_entities": []}, {"description": "Referred to Transportation.", "date": "2025-04-03", "organization_id": "~{\"classification\": \"lower\"}", "classification": ["referral-committee"], "related_entities": []}], "sponsorships": [{"name": "COMMITTEE ON TRANSPORTATION", "classification": "primary", "entity_type": "organization", "primary": true, "person_id": null, "organization_id": "~{\"name\": \"COMMITTEE ON TRANSPORTATION\"}"}], "related_bills": [], "versions": [{"note": "Introduced", "links": [{"url": "https://www.legis.iowa.gov/docs/publications/LGI/91/attachments/HF896.html", "media_type": "text/html"}, {"url": "https://www.legis.iowa.gov/docs/publications/LGI/91/HF896.pdf", "media_type": "application/pdf"}], "date": "", "classification": ""}], "documents": [], "citations": [], "sources": [{"url": "https://www.legis.iowa.gov/legislation/billTracking/billHistory?billName=HF 896&ga=91", "note": ""}], "extras": {}, "jurisdiction": {"id": "ocd-jurisdiction/country:us/state:ia/government", "name": "Iowa", "classification": "state", "division_id": "ocd-division/country:us/state:ia"}, "scraped_at": "2026-01-27T08:18:59+00:00", "_id": "d4acfccc-fb58-11f0-a697-3a200981a3b8"}