{"legislative_session": "2025-2026", "identifier": "HF 2078", "title": "A bill for an act relating to resident dependents not enrolled in a public school or receiving an educational savings account payment by creating an opportunity tax credit available against the individual income tax, creating a fund, making appropriations, and including effective date and retroactive applicability provisions.", "from_organization": "~{\"classification\": \"lower\"}", "classification": ["bill"], "subject": ["accounts", "appropriations", "dependent persons", "income taxes", "residence", "savings", "school finance", "schools", "students", "tax credits"], "abstracts": [], "other_titles": [], "other_identifiers": [], "actions": [{"description": "Introduced, referred to Education. H.J. 01/15.", "date": "2026-01-15", "organization_id": "~{\"classification\": \"lower\"}", "classification": ["introduction", "referral-committee"], "related_entities": []}], "sponsorships": [{"name": "FETT", "classification": "primary", "entity_type": "person", "primary": true, "person_id": "~{\"name\": \"FETT\"}", "organization_id": null}], "related_bills": [], "versions": [{"note": "Introduced", "links": [{"url": "https://www.legis.iowa.gov/docs/publications/LGI/91/attachments/HF2078.html", "media_type": "text/html"}, {"url": "https://www.legis.iowa.gov/docs/publications/LGI/91/HF2078.pdf", "media_type": "application/pdf"}], "date": "", "classification": ""}], "documents": [], "citations": [], "sources": [{"url": "https://www.legis.iowa.gov/legislation/billTracking/billHistory?billName=HF 2078&ga=91", "note": ""}], "extras": {}, "jurisdiction": {"id": "ocd-jurisdiction/country:us/state:ia/government", "name": "Iowa", "classification": "state", "division_id": "ocd-division/country:us/state:ia"}, "scraped_at": "2026-03-01T08:19:03+00:00", "_id": "4f227a42-1547-11f1-94b1-9a7bf93e9c75"}