{"legislative_session": "2025-2026", "identifier": "SF 2138", "title": "A bill for an act relating to prohibited activities in the administration of alcoholic beverage control by the department of revenue, and including effective date provisions.", "from_organization": "~{\"classification\": \"upper\"}", "classification": ["bill"], "subject": ["alcoholic beverages", "alcoholic beverages commission", "labor and employment", "manufacturing", "revenue department", "sales"], "abstracts": [], "other_titles": [], "other_identifiers": [], "actions": [{"description": "Introduced, placed on calendar.", "date": "2026-01-28", "organization_id": "~{\"classification\": \"upper\"}", "classification": ["introduction"], "related_entities": []}, {"description": "Committee report, approving bill.", "date": "2026-01-28", "organization_id": "~{\"classification\": \"upper\"}", "classification": ["committee-passage"], "related_entities": []}], "sponsorships": [{"name": "COMMITTEE ON STATE GOVERNMENT", "classification": "primary", "entity_type": "organization", "primary": true, "person_id": null, "organization_id": "~{\"name\": \"COMMITTEE ON STATE GOVERNMENT\"}"}], "related_bills": [], "versions": [{"note": "Introduced", "links": [{"url": "https://www.legis.iowa.gov/docs/publications/LGI/91/attachments/SF2138.html", "media_type": "text/html"}, {"url": "https://www.legis.iowa.gov/docs/publications/LGI/91/SF2138.pdf", "media_type": "application/pdf"}], "date": "", "classification": ""}], "documents": [], "citations": [], "sources": [{"url": "https://www.legis.iowa.gov/legislation/billTracking/billHistory?billName=SF 2138&ga=91", "note": ""}], "extras": {}, "jurisdiction": {"id": "ocd-jurisdiction/country:us/state:ia/government", "name": "Iowa", "classification": "state", "division_id": "ocd-division/country:us/state:ia"}, "scraped_at": "2026-02-22T08:18:56+00:00", "_id": "22132f0e-0fc7-11f1-848f-2a3dea4edf6d"}