{"legislative_session": "2025-2026", "identifier": "HF 2538", "title": "A bill for an act relating to education, including by modifying provisions related to the duties of the department of education, the discipline of students enrolled in school districts, charter schools, and innovation zone schools who exhibit disorderly conduct in the classroom, the responsibilities and powers of the department of education, school district teachers, and other educational staff related to students who have individualized education programs or plans under section 504 of the federal Rehabilitation Act, and school district professional development plans, and authorizing teachers to request a meeting of a student\u2019s individualized education program team.", "from_organization": "~{\"classification\": \"lower\"}", "classification": ["bill"], "subject": ["charter schools", "disorderly conduct", "education", "exhibitions", "individualized education program", "innovation zone schools", "meetings", "school districts", "schools", "students", "teachers"], "abstracts": [], "other_titles": [], "other_identifiers": [{"identifier": "ocd-bill-ia-2025_2026-hf2538"}], "actions": [{"description": "Introduced, placed on calendar. H.J. 02/16.", "date": "2026-02-16", "organization_id": "~{\"classification\": \"lower\"}", "classification": ["introduction"], "related_entities": []}], "sponsorships": [{"name": "COMMITTEE ON EDUCATION", "classification": "primary", "entity_type": "organization", "primary": true, "person_id": null, "organization_id": "~{\"name\": \"COMMITTEE ON EDUCATION\"}"}], "related_bills": [], "versions": [{"note": "Introduced", "links": [{"url": "https://www.legis.iowa.gov/docs/publications/LGI/91/attachments/HF2538.html", "media_type": "text/html"}, {"url": "https://www.legis.iowa.gov/docs/publications/LGI/91/HF2538.pdf", "media_type": "application/pdf"}], "date": "", "classification": ""}], "documents": [], "citations": [], "sources": [{"url": "https://www.legis.iowa.gov/legislation/billTracking/billHistory?billName=HF 2538&ga=91", "note": ""}], "extras": {}, "jurisdiction": {"id": "ocd-jurisdiction/country:us/state:ia/government", "name": "Iowa", "classification": "state", "division_id": "ocd-division/country:us/state:ia"}, "scraped_at": "2026-04-12T08:37:11+00:00", "_id": "cce7c08a-364a-11f1-aabd-66538b9ab9c6"}